<?xml version="1.0" encoding="UTF-8"?>
<beans xmlns="http://www.springframework.org/schema/beans"
       xmlns:xsi="http://www.w3.org/2001/XMLSchema-instance"
       xsi:schemaLocation="
       http://www.springframework.org/schema/beans http://www.springframework.org/schema/beans/spring-beans.xsd
       http://camel.apache.org/schema/spring       http://camel.apache.org/schema/spring/camel-spring.xsd">

    <camelContext id="context1" xmlns="http://camel.apache.org/schema/spring">

        <onException>
            <exception>java.lang.Exception</exception>
            <handled><constant>true</constant></handled>
            <setHeader headerName="Exchange.HTTP_RESPONSE_CODE">
                <constant>500</constant>
            </setHeader>
            <setBody>
                <simple>${exception.message}</simple>
            </setBody>
        </onException>

        <restConfiguration component="servlet" apiContextPath="/openapi.json"/>

        <rest id="rest1" path="/" enableCORS="true">
            <get id="openapi.json" produces="application/json" uri="openapi.json">
                <description>Gets the openapi document for this service</description>
                <route id="rest1-route1">
                    <setHeader id="setHeader-route1" headerName="Exchange.CONTENT_TYPE">
                        <constant>application/vnd.oai.openapi+json</constant>
                    </setHeader>
                    <setBody id="setBody-route1">
                        <simple>resource:classpath:openapi.json</simple>
                    </setBody>
                </route>
            </get>
        </rest>

        <rest id="rest2" path="{{swagger.basePath}}" bindingMode="json" enableCORS="true">
        {{& restXML}}
        </rest>

        {{#directEndpoints}}
        <route id="route-{{uuid}}">
            <from id="from-{{uuid}}" uri="{{.}}"/>
            <to id="to-{{uuid}}" uri="direct:501"/>
        </route>
        {{/directEndpoints}}

        <route id="route2">
            <from id="from-route2" uri="direct:501"/>
            <log id="log-route2" message="API operation not yet implemented: ${headers.CamelHttpMethod} ${headers.CamelHttpPath}"/>
            <setHeader id="setHeader-route2" headerName="Exchange.HTTP_RESPONSE_CODE">
                <constant>501</constant>
            </setHeader>
            <setBody id="setBody-route2">
                <simple>API operation not implemented: ${headers.CamelHttpMethod} ${headers.CamelHttpPath}</simple>
            </setBody>
        </route>

    </camelContext>
</beans>
